[
  {
    "name": "陈亦辰",
    "email": "chenyichen@example.com",
    "score": 85,
    "summary": "AI自动评估",
    "emailDraft": {
      "subject": null
    },
    "created_at": "2025-12-09T10:48:43.598Z",
    "status": "待面试",
    "interviewQuestions": [
      {
        "category": "技术",
        "difficulty": "中",
        "expected_points": [
          6,
          8,
          10
        ],
        "question": "请详细描述你从0到1搭建产品时，如何通过数据分析驱动产品决策？可以结合具体项目说明你是如何定义关键指标、收集数据并据此优化产品的。",
        "rationale": "针对候选人数据分析能力突出的优势，考察其数据驱动决策的实际应用能力，验证SQL+Python+Tableau技能在项目中的具体运用"
      },
      {
        "category": "项目",
        "difficulty": "高",
        "expected_points": [
          7,
          9,
          10
        ],
        "question": "请分享一个你在产品开发过程中遇到的重大挑战，你是如何协调研发、设计、测试等团队解决问题并确保项目按时交付的？",
        "rationale": "考察2年+工作经验下的项目管理和跨团队协作能力，验证敏捷开发流程的实际应用，同时评估问题解决和沟通协调能力"
      },
      {
        "category": "行为",
        "difficulty": "中",
        "expected_points": [
          5,
          7,
          9
        ],
        "question": "请举例说明你如何进行用户研究和需求分析，特别是如何从技术思维转向用户思维，确保产品功能真正满足用户需求的？",
        "rationale": "针对缺乏用户研究具体案例的弱点，考察用户需求洞察和分析能力，评估从技术背景向产品思维的转变程度"
      }
    ],
    "updated_at": "2025-12-10T06:23:46.855Z"
  },
  {
    "name": "陈宇",
    "email": "chenyu_pm@163.com",
    "score": 75,
    "summary": "AI自动评估",
    "emailDraft": {
      "subject": null
    },
    "created_at": "2025-12-10T05:08:35.932Z",
    "status": "待面试",
    "updated_at": "2025-12-10T06:55:58.960Z"
  },
  {
    "name": "林晓悦",
    "email": "easylife2567@gmail.com",
    "score": 85,
    "summary": "AI自动评估",
    "interviewQuestions": [
      {
        "category": "项目",
        "difficulty": "中",
        "expected_points": [
          6,
          8,
          10
        ],
        "question": "请详细描述你主导的一个完整产品上线案例，包括从需求调研到上线运营的全流程管理，并说明在这个过程中你如何协调开发、测试、设计等团队确保项目按时交付？",
        "rationale": "基于候选人简历中展示的完整产品全流程管理经验和跨部门协调能力优势，深入考察实际项目管理能力和团队协作经验"
      },
      {
        "category": "行为",
        "difficulty": "高",
        "expected_points": [
          7,
          9,
          10
        ],
        "question": "你在简历中提到'用户转化率提升15%'和'用户满意度从75%提升至85%'等量化成果，请具体说明这些数据背后的计算基础、时间周期以及你采取了哪些具体的产品优化措施来实现这些提升？",
        "rationale": "针对issues_found中'量化成果展示'的中等严重程度问题，深度考察数据背景和产品决策逻辑，验证量化成果的真实性和方法论"
      },
      {
        "category": "技术",
        "difficulty": "初",
        "expected_points": [
          5,
          7
        ],
        "question": "除了Axure和墨刀，你是否接触或使用过Sketch、Figma等现代产品设计工具？如果目前不熟悉，请阐述你的学习计划和如何快速适应新的设计工具生态？",
        "rationale": "针对issues_found中'技能工具广度'的未通过项，考察候选人对现代产品设计工具的认知和学习适应能力，评估技术技能的全面性"
      }
    ],
    "emailDraft": {
      "subject": "【北京心脏跳动科技有限公司】产品经理岗位面试邀请 - 致林晓悦",
      "content": "尊敬的林晓悦女士：\n\n您好！\n\n感谢您对北京心脏跳动科技有限公司产品经理岗位的关注。经过对您简历的认真评估，我们发现您在以下方面与我们的岗位要求高度契合：您拥有完整的产品全流程管理经验，从需求调研到上线运营的实战能力；精通Axure RP、墨刀等原型设计工具，具备独立输出高质量PRD文档的能力；熟练掌握敏捷开发流程，并拥有互联网科技行业的成功产品上线经历。这些优势与岗位要求的产品规划能力、跨部门协调能力以及数据分析能力完美匹配。\n\n我们诚挚邀请您参加面试，具体安排如下：\n- **面试时间**：2025年7月20日 上午9:00-11:00 或 下午2:00-4:00（请选择您方便的时间段）\n- **面试地点**：北京市朝阳区三间房乡梆子井公寓4号楼209\n- **面试形式**：一对一结构化面试，时长约60分钟\n\n**面试需准备材料**：\n- 身份证原件及复印件\n- 个人简历复印件\n- 相关资质证书（如有）\n\n**注意事项**：建议提前10分钟到达面试地点，以便完成登记手续。\n\n烦请您于2025年7月18日前回复本邮件，确认是否参加面试，回复格式为“林晓悦-产品经理-确认参加-意向时间：XX”（若无法参加也请同步告知）。我们将通过您提供的电话13811116295进行最终确认。\n\n若对面试安排有任何疑问，请联系HR张经理，电话：010-XXXXXXX，邮箱：hr@heartbeat-tech.com。\n\n期待您的回复，祝您面试顺利！\n\n顺祝商祺\n\n北京心脏跳动科技有限公司\n人力资源部\n2025年7月15日"
    },
    "created_at": "2025-12-10T06:23:47.286Z",
    "status": "待面试"
  },
  {
    "name": "林沐希",
    "email": "linmuxi@example.com",
    "score": 90,
    "summary": "AI自动评估",
    "interviewQuestions": [
      {
        "category": "项目",
        "difficulty": "高",
        "expected_points": [
          8,
          10,
          12
        ],
        "question": "请详细描述您在字节跳动作为核心项目负责人时，如何从0到1搭建产品并推动落地的完整流程，包括需求分析、产品设计、开发协调和上线后的数据跟踪优化？",
        "rationale": "基于候选人核心项目负责人经验和从0到1搭建经验的优势，深度考察产品全流程管理能力和实际项目执行细节"
      },
      {
        "category": "技术",
        "difficulty": "中",
        "expected_points": [
          7,
          9,
          11
        ],
        "question": "您提到建立了用户行为数据分析体系并提升了28%的用户满意度，请具体说明您是如何通过数据分析发现问题、制定优化策略并验证效果的？可以结合具体案例说明SQL和Python在其中的应用？",
        "rationale": "针对候选人数据驱动能力突出的优势，深入考察数据分析能力在实际产品优化中的具体应用和技术实现"
      },
      {
        "category": "行为",
        "difficulty": "中",
        "expected_points": [
          6,
          8,
          10
        ],
        "question": "作为产品助理，您在推动跨部门协作时遇到的最大挑战是什么？如何协调研发团队确保产品按时高质量交付？请分享一个具体的冲突处理案例？",
        "rationale": "针对候选人职位为产品助理而非产品经理的弱点，考察实际项目管理中的沟通协调能力和问题解决能力"
      }
    ],
    "emailDraft": {
      "subject": "【北京心脏跳动科技有限公司】产品经理面试邀请 - 致林沐希",
      "content": "尊敬的林沐希女士：\n\n您好！\n\n感谢您对北京心脏跳动科技有限公司产品经理岗位的关注。经过对您简历的认真评估，我们注意到您在清华大学优秀学历背景、字节跳动核心项目负责人经验以及突出的数据驱动决策能力方面表现卓越，特别是在产品设计流程工具使用、需求分析文档撰写、敏捷开发流程应用等方面与我们的岗位要求高度契合。您在字节跳动担任核心项目负责人期间积累的丰富经验，以及建立的用户行为数据分析体系，完全满足我们对产品经理岗位的核心能力要求。\n\n我们诚挚地邀请您参加面试，具体安排如下：\n**面试时间**：2025年3月20日 上午9:00-11:00 或 下午2:00-4:00\n**面试地点**：北京市朝阳区三间房乡梆子井公寓4号楼209\n**面试形式**：一对一结构化面试，预计时长60分钟\n\n请您携带以下材料参加面试：\n1. 身份证原件及复印件\n2. 个人简历复印件\n3. 相关学历、资质证书复印件\n4. 过往项目作品集（如有）\n\n建议您提前10分钟到达面试地点，以便顺利完成面试前的准备工作。如需调整面试安排，可直接通过邮箱linmuxi@example.com或电话13899996257与我们沟通。\n\n烦请您于2025年3月18日前回复本邮件，格式为'林沐希-产品经理-确认参加-意向时间：XX'，若无法参加也请同步告知，感谢您的配合。\n\n若您对面试安排有任何疑问，可联系HR招聘负责人，电话：010-XXXXXXX，邮箱：hr@heartbeat-tech.com。\n\n顺祝商祺！\n\n北京心脏跳动科技有限公司\n人力资源部\n2025年3月15日"
    },
    "created_at": "2025-12-10T06:55:59.644Z",
    "status": "待面试",
    "updated_at": "2025-12-10T10:08:05.819Z"
  }
]